Metadata-Version: 1.1
Name: repo2dockerspawner
Version: 0.0.2
Summary: Repo2Dockerspawner: A custom spawner for Jupyterhub.
Home-page: https://github.com/ideonate/repo2dockerspawner
Author: Ideonate
Author-email: dan@ideonate.com
License: BSD
Keywords: Interactive,Interpreter,Shell,Web
Platform: Linux
Platform: Mac OS X
Classifier: Intended Audience :: Developers
Classifier: Intended Audience :: System Administrators
Classifier: Intended Audience :: Science/Research
Classifier: License :: OSI Approved :: BSD License
Classifier: Programming Language :: Python
Classifier: Programming Language :: Python :: 3
